LICENSE
README.md
setup.cfg
setup.py
trucks_and_drones/__init__.py
trucks_and_drones/build_env.py
trucks_and_drones/build_env_old.py
trucks_and_drones/environment.py
trucks_and_drones/reward_calculator.py
trucks_and_drones/visualizer.py
trucks_and_drones/wacky_ppo.py
trucks_and_drones.egg-info/PKG-INFO
trucks_and_drones.egg-info/SOURCES.txt
trucks_and_drones.egg-info/dependency_links.txt
trucks_and_drones.egg-info/requires.txt
trucks_and_drones.egg-info/top_level.txt
trucks_and_drones/acts/__init__.py
trucks_and_drones/acts/_custom_acts.py
trucks_and_drones/acts/tsp_action.py
trucks_and_drones/acts/tsp_drone_action.py
trucks_and_drones/obs/__init__.py
trucks_and_drones/obs/_custom_obs.py
trucks_and_drones/obs/node_encoder_obs_1.py
trucks_and_drones/obs/node_encoder_obs_2.py
trucks_and_drones/obs/simple_obs.py
trucks_and_drones/obs/tsp_distances_obs.py
trucks_and_drones/simulation/__init__.py
trucks_and_drones/simulation/action_interpreter.py
trucks_and_drones/simulation/acts.py
trucks_and_drones/simulation/acts_backup.py
trucks_and_drones/simulation/auto_agent.py
trucks_and_drones/simulation/common_sim_func.py
trucks_and_drones/simulation/nodes.py
trucks_and_drones/simulation/obs.py
trucks_and_drones/simulation/positions.py
trucks_and_drones/simulation/restrictions.py
trucks_and_drones/simulation/simulation.py
trucks_and_drones/simulation/state_interpreter.py
trucks_and_drones/simulation/temp_database.py
trucks_and_drones/simulation/vehicles.py
trucks_and_drones/simulation/vehicles_backup.py