Metadata-Version: 2.1
Name: trucks-and-drones
Version: 0.0.6
Summary: A gym environment that simulates the travelling salesman or vehicle routing problem with drones or robots.
Home-page: https://github.com/maik97/trucks-and-drones
Author: Maik Schürmann
Author-email: maik.schuermann97@gmail.com
License: MIT
Download-URL: https://github.com/maik97/trucks-and-drones/archive/refs/tags/v_0.0.6.tar.gz
Keywords: tsp,vrp,tsp-d,vrp-d,travelling salesman problem,vehicle routing problem,rl,reinforcement learning,gym environment
Platform: UNKNOWN
Classifier: Development Status :: 3 - Alpha
Classifier: Intended Audience :: Developers
Classifier: Topic :: Software Development :: Build Tools
Classifier: License :: OSI Approved :: MIT License
Classifier: Programming Language :: Python :: 3.9
Classifier: Programming Language :: Python :: 3.8
Classifier: Programming Language :: Python :: 3.7
Classifier: Programming Language :: Python :: 3.6
License-File: LICENSE
